kyfkyf/__init__.py
kyfkyf-0.0.0.dist-info/METADATA
kyfkyf-0.0.0.dist-info/WHEEL
kyfkyf-0.0.0.dist-info/RECORD
